subprocrunner/__init__.py
subprocrunner/__version__.py
subprocrunner/_subprocess_runner.py
subprocrunner/_which.py
subprocrunner/error.py
subprocrunner/py.typed
subprocrunner/retry.py
subprocrunner/typing.py
subprocrunner/_logger/__init__.py
subprocrunner/_logger/_logger.py
subprocrunner/_logger/_null_logger.py
subprocrunner-2.0.1.dist-info/LICENSE
subprocrunner-2.0.1.dist-info/METADATA
subprocrunner-2.0.1.dist-info/WHEEL
subprocrunner-2.0.1.dist-info/top_level.txt
subprocrunner-2.0.1.dist-info/RECORD
